<annotation>
  <folder>train</folder>
  <filename>247</filename>
  <path>D:\Datasets\pile_dataset\train\247.jpg</path>
  <source>
    <database>Unknown</database>
  </source>
  <size>
    <width>640</width>
    <height>640</height>
    <depth>3</depth>
  </size>
  <segmented>0</segmented>
  <object>
    <name>trash</name>
    <pose>Unspecified</pose>
    <truncated>0</truncated>
    <difficult>0</difficult>
    <bndbox>
      <xmin>1</xmin>
      <ymin>401</ymin>
      <xmax>167</xmax>
      <ymax>504</ymax>
    </bndbox>
  </object>
  <object>
    <name>trash</name>
    <pose>Unspecified</pose>
    <truncated>0</truncated>
    <difficult>0</difficult>
    <bndbox>
      <xmin>542</xmin>
      <ymin>412</ymin>
      <xmax>640</xmax>
      <ymax>477</ymax>
    </bndbox>
  </object>
</annotation>