<annotation>
  <folder>train</folder>
  <filename>265</filename>
  <path>D:\Datasets\pile_dataset\train\265.jpg</path>
  <source>
    <database>Unknown</database>
  </source>
  <size>
    <width>640</width>
    <height>640</height>
    <depth>3</depth>
  </size>
  <segmented>0</segmented>
  <object>
    <name>trash</name>
    <pose>Unspecified</pose>
    <truncated>0</truncated>
    <difficult>0</difficult>
    <bndbox>
      <xmin>102</xmin>
      <ymin>492</ymin>
      <xmax>317</xmax>
      <ymax>633</ymax>
    </bndbox>
  </object>
  <object>
    <name>trash</name>
    <pose>Unspecified</pose>
    <truncated>0</truncated>
    <difficult>0</difficult>
    <bndbox>
      <xmin>390</xmin>
      <ymin>548</ymin>
      <xmax>488</xmax>
      <ymax>603</ymax>
    </bndbox>
  </object>
</annotation>